powerpay_protos/__init__.py
powerpay_protos/device_pb2.py
powerpay_protos/device_pb2.pyi
powerpay_protos/device_pb2_grpc.py
powerpay_protos/integration_pb2.py
powerpay_protos/integration_pb2.pyi
powerpay_protos/integration_pb2_grpc.py
powerpay_protos/measurement_pb2.py
powerpay_protos/measurement_pb2.pyi
powerpay_protos/telemetry_pb2.py
powerpay_protos/telemetry_pb2.pyi
powerpay_protos-0.3.7.dist-info/METADATA
powerpay_protos-0.3.7.dist-info/WHEEL
powerpay_protos-0.3.7.dist-info/RECORD
