Metadata-Version: 2.4
Name: powerpay_protos
Version: 0.3.7
Summary: Compiled protobuf files for PowerPay
Author: Jørgen Rørvik
Author-email: 60797691+jorgror@users.noreply.github.com
Requires-Python: >=3.12,<4.0
Classifier: Programming Language :: Python :: 3
Classifier: Programming Language :: Python :: 3.12
Classifier: Programming Language :: Python :: 3.13
Classifier: Programming Language :: Python :: 3.14
Requires-Dist: grpcio (>=1.68.1,<2.0.0)
Requires-Dist: protobuf (>=5.28.1,<6.0.0)
